acora/__init__.py
acora/_acora.cpython-310-darwin.so
acora/_acora.py
acora/_cacora.cpython-310-darwin.so
acora-2.5.dist-info/LICENSE.txt
acora-2.5.dist-info/METADATA
acora-2.5.dist-info/WHEEL
acora-2.5.dist-info/top_level.txt
acora-2.5.dist-info/RECORD
