Metadata-Version: 2.1
Name: acora
Version: 2.5
Summary: Fast multi-keyword search engine for text strings
Home-page: http://pypi.python.org/pypi/acora
Author: Stefan Behnel
Author-email: stefan_ml@behnel.de
Maintainer: Stefan Behnel
Maintainer-email: stefan_ml@behnel.de
Classifier: Intended Audience :: Developers
Classifier: Intended Audience :: Information Technology
Classifier: License :: OSI Approved :: BSD License
Classifier: Programming Language :: Cython
Classifier: Programming Language :: Python :: 2
Classifier: Programming Language :: Python :: 2.7
Classifier: Programming Language :: Python :: 3
Classifier: Programming Language :: Python :: 3.6
Classifier: Programming Language :: Python :: 3.7
Classifier: Programming Language :: Python :: 3.8
Classifier: Programming Language :: Python :: 3.9
Classifier: Programming Language :: Python :: 3.10
Classifier: Programming Language :: Python :: 3.11
Classifier: Programming Language :: Python :: 3.12
Classifier: Programming Language :: Python :: 3.13
Classifier: Operating System :: OS Independent
Classifier: Topic :: Text Processing
License-File: LICENSE.txt
Provides-Extra: source
Requires-Dist: Cython>=3.0.11; extra == "source"
